{
	"info": {
		"_postman_id": "ded46a92-9fcd-4bc8-a981-cc6ede3f480c",
		"name": "Fazz008",
		"schema": "https://schema.getpostman.com/json/collection/v2.1.0/collection.json",
		"_exporter_id": "18051667"
	},
	"item": [
		{
			"name": "Get All Users",
			"request": {
				"method": "GET",
				"header": [],
				"url": {
					"raw": "http://localhost:8000/users",
					"protocol": "http",
					"host": [
						"localhost"
					],
					"port": "8000",
					"path": [
						"users"
					]
				}
			},
			"response": []
		},
		{
			"name": "GET Users By Id",
			"request": {
				"method": "GET",
				"header": [],
				"url": {
					"raw": "http://localhost:8000/users/find/:id",
					"protocol": "http",
					"host": [
						"localhost"
					],
					"port": "8000",
					"path": [
						"users",
						"find",
						":id"
					],
					"variable": [
						{
							"key": "id",
							"value": "1"
						}
					]
				}
			},
			"response": []
		},
		{
			"name": "Wellcome",
			"request": {
				"method": "GET",
				"header": [],
				"url": {
					"raw": "http://localhost:8000",
					"protocol": "http",
					"host": [
						"localhost"
					],
					"port": "8000"
				}
			},
			"response": []
		},
		{
			"name": "Create users",
			"request": {
				"method": "POST",
				"header": [],
				"body": {
					"mode": "urlencoded",
					"urlencoded": [
						{
							"key": "email",
							"value": "create@gmail.com",
							"type": "text"
						},
						{
							"key": "fullname",
							"value": "create",
							"type": "text"
						}
					]
				},
				"url": {
					"raw": "http://localhost:8000/users",
					"protocol": "http",
					"host": [
						"localhost"
					],
					"port": "8000",
					"path": [
						"users"
					]
				}
			},
			"response": []
		},
		{
			"name": "Edit Users By Id",
			"request": {
				"method": "PATCH",
				"header": [],
				"body": {
					"mode": "urlencoded",
					"urlencoded": [
						{
							"key": "email",
							"value": "edit@gmail.com",
							"type": "text"
						},
						{
							"key": "fullname",
							"value": "edit",
							"type": "text"
						}
					]
				},
				"url": {
					"raw": "http://localhost:8000/users/:id",
					"protocol": "http",
					"host": [
						"localhost"
					],
					"port": "8000",
					"path": [
						"users",
						":id"
					],
					"variable": [
						{
							"key": "id",
							"value": "1"
						}
					]
				}
			},
			"response": []
		},
		{
			"name": "Delete Users By Id",
			"request": {
				"method": "DELETE",
				"header": [],
				"url": {
					"raw": "http://localhost:8000/users/:id",
					"protocol": "http",
					"host": [
						"localhost"
					],
					"port": "8000",
					"path": [
						"users",
						":id"
					],
					"variable": [
						{
							"key": "id",
							"value": null
						}
					]
				}
			},
			"response": []
		}
	]
}